yazdl/__init__.py
yazdl/core/__init__.py
yazdl/core/headers.py
yazdl/core/main.py
yazdl/core/options.py
yazdl/core/zoom_downloader.py
yazdl/data/__init__.py
yazdl/data/streams.py
yazdl/handlers/__init__.py
yazdl/handlers/data_handler.py
yazdl/handlers/parser.py
yazdl/handlers/url_handler.py
yazdl-0.1.0.data/scripts/yazdl
yazdl-0.1.0.dist-info/LICENSE
yazdl-0.1.0.dist-info/METADATA
yazdl-0.1.0.dist-info/WHEEL
yazdl-0.1.0.dist-info/top_level.txt
yazdl-0.1.0.dist-info/RECORD
