Metadata-Version: 2.1
Name: yazdl
Version: 0.1.0
Summary: Download zoom recordings.
Home-page: https://github.com/pvpscript/yazdl
Author: pvpscript
Project-URL: Bug Reports, https://github.com/pvpscript/yazdl/issues
Project-URL: Source, https://github.com/pvpscript/yazdl
Keywords: zoom,recording,downloader
Classifier: Environment :: Console
Classifier: Intended Audience :: Developers
Classifier: Intended Audience :: End Users/Desktop
Classifier: Intended Audience :: System Administrators
Classifier: License :: OSI Approved :: MIT License
Classifier: Operating System :: Unix
Classifier: Programming Language :: Python :: 3
Classifier: Topic :: Utilities
Requires-Python: >=3.9
License-File: LICENSE
Requires-Dist: certifi >=2024.2.2
Requires-Dist: charset-normalizer >=3.3.2
Requires-Dist: idna >=3.7
Requires-Dist: requests >=2.31.0
Requires-Dist: setuptools >=69.5.1
Requires-Dist: urllib3 >=2.2.1
Requires-Dist: wheel >=0.43.0
